{
    "1": {
        "tl": [
            14.43,
            28.63
        ],
        "tr": [
            20.05,
            28.69
        ],
        "br": [
            20.0,
            36.2
        ],
        "bl": [
            14.38,
            36.19
        ],
        "type": "grid"
    },
    "2": {
        "tl": [
            20.05,
            28.69
        ],
        "tr": [
            25.68,
            28.62
        ],
        "br": [
            25.69,
            36.26
        ],
        "bl": [
            20.0,
            36.2
        ],
        "type": "grid"
    },
    "3": {
        "tl": [
            25.68,
            28.62
        ],
        "tr": [
            31.44,
            28.68
        ],
        "br": [
            31.38,
            36.23
        ],
        "bl": [
            25.69,
            36.26
        ],
        "type": "grid"
    },
    "4": {
        "tl": [
            31.44,
            28.68
        ],
        "tr": [
            37.2,
            28.61
        ],
        "br": [
            37.16,
            36.2
        ],
        "bl": [
            31.38,
            36.23
        ],
        "type": "grid"
    },
    "5": {
        "tl": [
            37.2,
            28.61
        ],
        "tr": [
            42.97,
            28.67
        ],
        "br": [
            42.93,
            36.19
        ],
        "bl": [
            37.16,
            36.2
        ],
        "type": "grid"
    },
    "6": {
        "tl": [
            42.97,
            28.67
        ],
        "tr": [
            48.74,
            28.6
        ],
        "br": [
            48.76,
            36.26
        ],
        "bl": [
            42.93,
            36.19
        ],
        "type": "grid"
    },
    "7": {
        "tl": [
            48.74,
            28.6
        ],
        "tr": [
            54.49,
            28.67
        ],
        "br": [
            54.42,
            36.25
        ],
        "bl": [
            48.76,
            36.26
        ],
        "type": "grid"
    },
    "8": {
        "tl": [
            141.37,
            28.78
        ],
        "tr": [
            147.1,
            28.77
        ],
        "br": [
            147.18,
            36.42
        ],
        "bl": [
            141.39,
            36.36
        ],
        "type": "grid"
    },
    "9": {
        "tl": [
            147.1,
            28.77
        ],
        "tr": [
            152.83,
            28.77
        ],
        "br": [
            152.85,
            36.41
        ],
        "bl": [
            147.18,
            36.42
        ],
        "type": "grid"
    },
    "10": {
        "tl": [
            152.83,
            28.77
        ],
        "tr": [
            158.56,
            28.76
        ],
        "br": [
            158.65,
            36.41
        ],
        "bl": [
            152.85,
            36.41
        ],
        "type": "grid"
    },
    "11": {
        "tl": [
            158.56,
            28.76
        ],
        "tr": [
            164.24,
            28.76
        ],
        "br": [
            164.33,
            36.41
        ],
        "bl": [
            158.65,
            36.41
        ],
        "type": "grid"
    },
    "12": {
        "tl": [
            164.24,
            28.76
        ],
        "tr": [
            170.04,
            28.81
        ],
        "br": [
            170.06,
            36.45
        ],
        "bl": [
            164.33,
            36.41
        ],
        "type": "grid"
    },
    "13": {
        "tl": [
            14.43,
            56.74
        ],
        "tr": [
            20.05,
            56.73
        ],
        "br": [
            20.0,
            64.34
        ],
        "bl": [
            14.36,
            64.33
        ],
        "type": "grid"
    },
    "14": {
        "tl": [
            20.05,
            56.73
        ],
        "tr": [
            25.76,
            56.8
        ],
        "br": [
            25.71,
            64.41
        ],
        "bl": [
            20.0,
            64.34
        ],
        "type": "grid"
    },
    "15": {
        "tl": [
            25.76,
            56.8
        ],
        "tr": [
            31.47,
            56.74
        ],
        "br": [
            31.42,
            64.36
        ],
        "bl": [
            25.71,
            64.41
        ],
        "type": "grid"
    },
    "16": {
        "tl": [
            31.47,
            56.74
        ],
        "tr": [
            37.24,
            56.81
        ],
        "br": [
            37.2,
            64.43
        ],
        "bl": [
            31.42,
            64.36
        ],
        "type": "grid"
    },
    "17": {
        "tl": [
            37.24,
            56.81
        ],
        "tr": [
            42.96,
            56.76
        ],
        "br": [
            42.98,
            64.38
        ],
        "bl": [
            37.2,
            64.43
        ],
        "type": "grid"
    },
    "18": {
        "tl": [
            42.96,
            56.76
        ],
        "tr": [
            48.86,
            56.83
        ],
        "br": [
            48.83,
            64.45
        ],
        "bl": [
            42.98,
            64.38
        ],
        "type": "grid"
    },
    "19": {
        "tl": [
            77.97,
            56.92
        ],
        "tr": [
            83.72,
            56.99
        ],
        "br": [
            83.77,
            64.57
        ],
        "bl": [
            77.95,
            64.5
        ],
        "type": "grid"
    },
    "20": {
        "tl": [
            83.72,
            56.99
        ],
        "tr": [
            89.54,
            56.94
        ],
        "br": [
            89.53,
            64.58
        ],
        "bl": [
            83.77,
            64.57
        ],
        "type": "grid"
    },
    "21": {
        "tl": [
            89.54,
            56.94
        ],
        "tr": [
            95.36,
            57.01
        ],
        "br": [
            95.35,
            64.66
        ],
        "bl": [
            89.53,
            64.58
        ],
        "type": "grid"
    },
    "22": {
        "tl": [
            141.59,
            57.06
        ],
        "tr": [
            147.33,
            57.12
        ],
        "br": [
            147.36,
            64.8
        ],
        "bl": [
            141.62,
            64.73
        ],
        "type": "grid"
    },
    "23": {
        "tl": [
            147.33,
            57.12
        ],
        "tr": [
            153.06,
            57.15
        ],
        "br": [
            153.15,
            64.86
        ],
        "bl": [
            147.36,
            64.8
        ],
        "type": "grid"
    },
    "24": {
        "tl": [
            14.34,
            84.83
        ],
        "tr": [
            20.04,
            84.86
        ],
        "br": [
            20.0,
            92.55
        ],
        "bl": [
            14.29,
            92.47
        ],
        "type": "grid"
    },
    "25": {
        "tl": [
            141.82,
            85.47
        ],
        "tr": [
            147.57,
            85.48
        ],
        "br": [
            147.59,
            93.13
        ],
        "bl": [
            141.84,
            93.12
        ],
        "type": "grid"
    },
    "26": {
        "tl": [
            147.57,
            85.48
        ],
        "tr": [
            153.39,
            85.5
        ],
        "br": [
            153.42,
            93.22
        ],
        "bl": [
            147.59,
            93.13
        ],
        "type": "grid"
    },
    "27": {
        "tl": [
            153.39,
            85.5
        ],
        "tr": [
            159.13,
            85.53
        ],
        "br": [
            159.24,
            93.24
        ],
        "bl": [
            153.42,
            93.22
        ],
        "type": "grid"
    },
    "28": {
        "tl": [
            14.33,
            113.12
        ],
        "tr": [
            20.06,
            113.21
        ],
        "br": [
            19.94,
            120.89
        ],
        "bl": [
            14.27,
            120.86
        ],
        "type": "grid"
    },
    "29": {
        "tl": [
            20.06,
            113.21
        ],
        "tr": [
            25.79,
            113.3
        ],
        "br": [
            25.72,
            120.95
        ],
        "bl": [
            19.94,
            120.89
        ],
        "type": "grid"
    },
    "30": {
        "tl": [
            25.79,
            113.3
        ],
        "tr": [
            31.46,
            113.27
        ],
        "br": [
            31.42,
            120.95
        ],
        "bl": [
            25.72,
            120.95
        ],
        "type": "grid"
    },
    "31": {
        "tl": [
            31.46,
            113.27
        ],
        "tr": [
            37.2,
            113.36
        ],
        "br": [
            37.22,
            120.99
        ],
        "bl": [
            31.42,
            120.95
        ],
        "type": "grid"
    },
    "32": {
        "tl": [
            37.2,
            113.36
        ],
        "tr": [
            43.04,
            113.34
        ],
        "br": [
            43.03,
            121.02
        ],
        "bl": [
            37.22,
            120.99
        ],
        "type": "grid"
    },
    "33": {
        "tl": [
            78.2,
            113.59
        ],
        "tr": [
            83.96,
            113.6
        ],
        "br": [
            83.95,
            121.31
        ],
        "bl": [
            78.17,
            121.28
        ],
        "type": "grid"
    },
    "34": {
        "tl": [
            83.96,
            113.6
        ],
        "tr": [
            89.8,
            113.69
        ],
        "br": [
            89.79,
            121.41
        ],
        "bl": [
            83.95,
            121.31
        ],
        "type": "grid"
    },
    "35": {
        "tl": [
            89.8,
            113.69
        ],
        "tr": [
            95.57,
            113.75
        ],
        "br": [
            95.64,
            121.44
        ],
        "bl": [
            89.79,
            121.41
        ],
        "type": "grid"
    },
    "36": {
        "tl": [
            95.57,
            113.75
        ],
        "tr": [
            101.38,
            113.75
        ],
        "br": [
            101.38,
            121.47
        ],
        "bl": [
            95.64,
            121.44
        ],
        "type": "grid"
    },
    "37": {
        "tl": [
            101.38,
            113.75
        ],
        "tr": [
            107.17,
            113.84
        ],
        "br": [
            107.17,
            121.5
        ],
        "bl": [
            101.38,
            121.47
        ],
        "type": "grid"
    },
    "38": {
        "tl": [
            107.17,
            113.84
        ],
        "tr": [
            112.97,
            113.8
        ],
        "br": [
            113.04,
            121.53
        ],
        "bl": [
            107.17,
            121.5
        ],
        "type": "grid"
    },
    "39": {
        "tl": [
            112.97,
            113.8
        ],
        "tr": [
            118.88,
            113.91
        ],
        "br": [
            118.83,
            121.61
        ],
        "bl": [
            113.04,
            121.53
        ],
        "type": "grid"
    },
    "40": {
        "tl": [
            142.04,
            114.01
        ],
        "tr": [
            147.81,
            114.1
        ],
        "br": [
            147.83,
            121.79
        ],
        "bl": [
            142.06,
            121.76
        ],
        "type": "grid"
    },
    "41": {
        "tl": [
            147.81,
            114.1
        ],
        "tr": [
            153.64,
            114.13
        ],
        "br": [
            153.67,
            121.88
        ],
        "bl": [
            147.83,
            121.79
        ],
        "type": "grid"
    },
    "42": {
        "tl": [
            153.64,
            114.13
        ],
        "tr": [
            159.48,
            114.16
        ],
        "br": [
            159.45,
            121.91
        ],
        "bl": [
            153.67,
            121.88
        ],
        "type": "grid"
    },
    "43": {
        "tl": [
            159.48,
            114.16
        ],
        "tr": [
            165.18,
            114.21
        ],
        "br": [
            165.17,
            121.94
        ],
        "bl": [
            159.45,
            121.91
        ],
        "type": "grid"
    },
    "44": {
        "tl": [
            165.18,
            114.21
        ],
        "tr": [
            170.91,
            114.21
        ],
        "br": [
            171.02,
            121.97
        ],
        "bl": [
            165.17,
            121.94
        ],
        "type": "grid"
    },
    "45": {
        "tl": [
            170.91,
            114.21
        ],
        "tr": [
            176.7,
            114.3
        ],
        "br": [
            176.75,
            122.01
        ],
        "bl": [
            171.02,
            121.97
        ],
        "type": "grid"
    },
    "46": {
        "tl": [
            176.7,
            114.3
        ],
        "tr": [
            182.62,
            114.27
        ],
        "br": [
            182.73,
            122.04
        ],
        "bl": [
            176.75,
            122.01
        ],
        "type": "grid"
    },
    "47": {
        "tl": [
            182.62,
            114.27
        ],
        "tr": [
            188.4,
            114.32
        ],
        "br": [
            188.47,
            122.07
        ],
        "bl": [
            182.73,
            122.04
        ],
        "type": "grid"
    },
    "48": {
        "tl": [
            14.32,
            141.67
        ],
        "tr": [
            20.0,
            141.77
        ],
        "br": [
            20.0,
            149.43
        ],
        "bl": [
            14.2,
            149.32
        ],
        "type": "grid"
    },
    "49": {
        "tl": [
            20.0,
            141.77
        ],
        "tr": [
            25.74,
            141.75
        ],
        "br": [
            25.75,
            149.47
        ],
        "bl": [
            20.0,
            149.43
        ],
        "type": "grid"
    },
    "50": {
        "tl": [
            25.74,
            141.75
        ],
        "tr": [
            31.49,
            141.85
        ],
        "br": [
            31.44,
            149.51
        ],
        "bl": [
            25.75,
            149.47
        ],
        "type": "grid"
    },
    "51": {
        "tl": [
            31.49,
            141.85
        ],
        "tr": [
            37.24,
            141.83
        ],
        "br": [
            37.2,
            149.55
        ],
        "bl": [
            31.44,
            149.51
        ],
        "type": "grid"
    },
    "52": {
        "tl": [
            37.24,
            141.83
        ],
        "tr": [
            43.06,
            141.93
        ],
        "br": [
            43.08,
            149.6
        ],
        "bl": [
            37.2,
            149.55
        ],
        "type": "grid"
    },
    "53": {
        "tl": [
            43.06,
            141.93
        ],
        "tr": [
            48.95,
            141.91
        ],
        "br": [
            48.91,
            149.64
        ],
        "bl": [
            43.08,
            149.6
        ],
        "type": "grid"
    },
    "54": {
        "tl": [
            48.95,
            141.91
        ],
        "tr": [
            54.71,
            142.01
        ],
        "br": [
            54.62,
            149.75
        ],
        "bl": [
            48.91,
            149.64
        ],
        "type": "grid"
    },
    "55": {
        "tl": [
            78.32,
            142.18
        ],
        "tr": [
            84.11,
            142.28
        ],
        "br": [
            84.1,
            149.97
        ],
        "bl": [
            78.3,
            149.87
        ],
        "type": "grid"
    },
    "56": {
        "tl": [
            84.11,
            142.28
        ],
        "tr": [
            89.91,
            142.32
        ],
        "br": [
            89.89,
            150.08
        ],
        "bl": [
            84.1,
            149.97
        ],
        "type": "grid"
    },
    "57": {
        "tl": [
            89.91,
            142.32
        ],
        "tr": [
            95.7,
            142.36
        ],
        "br": [
            95.74,
            150.09
        ],
        "bl": [
            89.89,
            150.08
        ],
        "type": "grid"
    },
    "58": {
        "tl": [
            95.7,
            142.36
        ],
        "tr": [
            101.51,
            142.47
        ],
        "br": [
            101.57,
            150.17
        ],
        "bl": [
            95.74,
            150.09
        ],
        "type": "grid"
    },
    "59": {
        "tl": [
            101.51,
            142.47
        ],
        "tr": [
            107.29,
            142.46
        ],
        "br": [
            107.32,
            150.27
        ],
        "bl": [
            101.57,
            150.17
        ],
        "type": "grid"
    },
    "60": {
        "tl": [
            142.27,
            142.75
        ],
        "tr": [
            148.11,
            142.79
        ],
        "br": [
            148.13,
            150.57
        ],
        "bl": [
            142.35,
            150.53
        ],
        "type": "grid"
    },
    "61": {
        "tl": [
            148.11,
            142.79
        ],
        "tr": [
            153.95,
            142.89
        ],
        "br": [
            153.98,
            150.68
        ],
        "bl": [
            148.13,
            150.57
        ],
        "type": "grid"
    },
    "62": {
        "tl": [
            153.95,
            142.89
        ],
        "tr": [
            159.68,
            142.93
        ],
        "br": [
            159.78,
            150.72
        ],
        "bl": [
            153.98,
            150.68
        ],
        "type": "grid"
    },
    "63": {
        "tl": [
            159.68,
            142.93
        ],
        "tr": [
            165.47,
            142.97
        ],
        "br": [
            165.51,
            150.76
        ],
        "bl": [
            159.78,
            150.72
        ],
        "type": "grid"
    },
    "64": {
        "tl": [
            165.47,
            142.97
        ],
        "tr": [
            171.21,
            143.07
        ],
        "br": [
            171.25,
            150.81
        ],
        "bl": [
            165.51,
            150.76
        ],
        "type": "grid"
    },
    "65": {
        "tl": [
            171.21,
            143.07
        ],
        "tr": [
            177.07,
            143.05
        ],
        "br": [
            177.12,
            150.85
        ],
        "bl": [
            171.25,
            150.81
        ],
        "type": "grid"
    },
    "66": {
        "tl": [
            177.07,
            143.05
        ],
        "tr": [
            182.94,
            143.15
        ],
        "br": [
            183.05,
            150.9
        ],
        "bl": [
            177.12,
            150.85
        ],
        "type": "grid"
    },
    "67": {
        "tl": [
            14.27,
            170.24
        ],
        "tr": [
            20.06,
            170.34
        ],
        "br": [
            19.94,
            178.09
        ],
        "bl": [
            14.25,
            177.98
        ],
        "type": "grid"
    },
    "68": {
        "tl": [
            142.56,
            171.63
        ],
        "tr": [
            148.35,
            171.74
        ],
        "br": [
            148.37,
            179.5
        ],
        "bl": [
            142.58,
            179.38
        ],
        "type": "grid"
    },
    "69": {
        "tl": [
            148.35,
            171.74
        ],
        "tr": [
            154.27,
            171.73
        ],
        "br": [
            154.24,
            179.55
        ],
        "bl": [
            148.37,
            179.5
        ],
        "type": "grid"
    },
    "70": {
        "tl": [
            154.27,
            171.73
        ],
        "tr": [
            160.01,
            171.84
        ],
        "br": [
            160.11,
            179.67
        ],
        "bl": [
            154.24,
            179.55
        ],
        "type": "grid"
    },
    "71": {
        "tl": [
            160.01,
            171.84
        ],
        "tr": [
            165.75,
            171.83
        ],
        "br": [
            165.85,
            179.72
        ],
        "bl": [
            160.11,
            179.67
        ],
        "type": "grid"
    },
    "72": {
        "tl": [
            14.25,
            198.82
        ],
        "tr": [
            20.0,
            198.92
        ],
        "br": [
            19.95,
            206.71
        ],
        "bl": [
            14.19,
            206.56
        ],
        "type": "grid"
    },
    "73": {
        "tl": [
            20.0,
            198.92
        ],
        "tr": [
            25.83,
            198.98
        ],
        "br": [
            25.78,
            206.71
        ],
        "bl": [
            19.95,
            206.71
        ],
        "type": "grid"
    },
    "74": {
        "tl": [
            25.83,
            198.98
        ],
        "tr": [
            31.49,
            199.04
        ],
        "br": [
            31.44,
            206.84
        ],
        "bl": [
            25.78,
            206.71
        ],
        "type": "grid"
    },
    "75": {
        "tl": [
            78.6,
            199.56
        ],
        "tr": [
            84.35,
            199.69
        ],
        "br": [
            84.34,
            207.51
        ],
        "bl": [
            78.53,
            207.37
        ],
        "type": "grid"
    },
    "76": {
        "tl": [
            84.35,
            199.69
        ],
        "tr": [
            90.24,
            199.81
        ],
        "br": [
            90.17,
            207.51
        ],
        "bl": [
            84.34,
            207.51
        ],
        "type": "grid"
    },
    "77": {
        "tl": [
            90.24,
            199.81
        ],
        "tr": [
            96.06,
            199.82
        ],
        "br": [
            96.0,
            207.64
        ],
        "bl": [
            90.17,
            207.51
        ],
        "type": "grid"
    },
    "78": {
        "tl": [
            96.06,
            199.82
        ],
        "tr": [
            101.83,
            199.94
        ],
        "br": [
            101.83,
            207.77
        ],
        "bl": [
            96.0,
            207.64
        ],
        "type": "grid"
    },
    "79": {
        "tl": [
            101.83,
            199.94
        ],
        "tr": [
            107.67,
            199.94
        ],
        "br": [
            107.67,
            207.78
        ],
        "bl": [
            101.83,
            207.77
        ],
        "type": "grid"
    },
    "80": {
        "tl": [
            107.67,
            199.94
        ],
        "tr": [
            113.57,
            200.07
        ],
        "br": [
            113.51,
            207.91
        ],
        "bl": [
            107.67,
            207.78
        ],
        "type": "grid"
    },
    "81": {
        "tl": [
            113.57,
            200.07
        ],
        "tr": [
            119.42,
            200.13
        ],
        "br": [
            119.36,
            207.91
        ],
        "bl": [
            113.51,
            207.91
        ],
        "type": "grid"
    },
    "82": {
        "tl": [
            119.42,
            200.13
        ],
        "tr": [
            125.21,
            200.19
        ],
        "br": [
            125.22,
            208.04
        ],
        "bl": [
            119.36,
            207.91
        ],
        "type": "grid"
    },
    "83": {
        "tl": [
            142.85,
            200.45
        ],
        "tr": [
            148.73,
            200.53
        ],
        "br": [
            148.74,
            208.31
        ],
        "bl": [
            142.87,
            208.24
        ],
        "type": "grid"
    },
    "84": {
        "tl": [
            148.73,
            200.53
        ],
        "tr": [
            154.53,
            200.57
        ],
        "br": [
            154.56,
            208.44
        ],
        "bl": [
            148.74,
            208.31
        ],
        "type": "grid"
    },
    "85": {
        "tl": [
            154.53,
            200.57
        ],
        "tr": [
            160.34,
            200.7
        ],
        "br": [
            160.38,
            208.44
        ],
        "bl": [
            154.56,
            208.44
        ],
        "type": "grid"
    },
    "86": {
        "tl": [
            160.34,
            200.7
        ],
        "tr": [
            166.1,
            200.7
        ],
        "br": [
            166.14,
            208.57
        ],
        "bl": [
            160.38,
            208.44
        ],
        "type": "grid"
    },
    "87": {
        "tl": [
            166.1,
            200.7
        ],
        "tr": [
            171.92,
            200.82
        ],
        "br": [
            171.97,
            208.69
        ],
        "bl": [
            166.14,
            208.57
        ],
        "type": "grid"
    },
    "88": {
        "tl": [
            171.92,
            200.82
        ],
        "tr": [
            177.69,
            200.89
        ],
        "br": [
            177.8,
            208.7
        ],
        "bl": [
            171.97,
            208.69
        ],
        "type": "grid"
    },
    "89": {
        "tl": [
            177.69,
            200.89
        ],
        "tr": [
            183.71,
            200.95
        ],
        "br": [
            183.83,
            208.83
        ],
        "bl": [
            177.8,
            208.7
        ],
        "type": "grid"
    },
    "90": {
        "tl": [
            183.71,
            200.95
        ],
        "tr": [
            189.62,
            200.95
        ],
        "br": [
            189.67,
            208.83
        ],
        "bl": [
            183.83,
            208.83
        ],
        "type": "grid"
    },
    "91": {
        "tl": [
            14.28,
            227.62
        ],
        "tr": [
            20.06,
            227.76
        ],
        "br": [
            20.01,
            235.58
        ],
        "bl": [
            14.24,
            235.43
        ],
        "type": "grid"
    },
    "92": {
        "tl": [
            20.06,
            227.76
        ],
        "tr": [
            25.85,
            227.77
        ],
        "br": [
            25.74,
            235.6
        ],
        "bl": [
            20.01,
            235.58
        ],
        "type": "grid"
    },
    "93": {
        "tl": [
            25.85,
            227.77
        ],
        "tr": [
            31.51,
            227.9
        ],
        "br": [
            31.53,
            235.67
        ],
        "bl": [
            25.74,
            235.6
        ],
        "type": "grid"
    },
    "94": {
        "tl": [
            31.51,
            227.9
        ],
        "tr": [
            37.37,
            227.92
        ],
        "br": [
            37.33,
            235.75
        ],
        "bl": [
            31.53,
            235.67
        ],
        "type": "grid"
    },
    "95": {
        "tl": [
            37.37,
            227.92
        ],
        "tr": [
            43.23,
            228.06
        ],
        "br": [
            43.19,
            235.83
        ],
        "bl": [
            37.33,
            235.75
        ],
        "type": "grid"
    },
    "96": {
        "tl": [
            43.23,
            228.06
        ],
        "tr": [
            49.03,
            228.07
        ],
        "br": [
            49.06,
            235.97
        ],
        "bl": [
            43.19,
            235.83
        ],
        "type": "grid"
    },
    "97": {
        "tl": [
            78.7,
            228.53
        ],
        "tr": [
            84.42,
            228.55
        ],
        "br": [
            84.49,
            236.39
        ],
        "bl": [
            78.66,
            236.31
        ],
        "type": "grid"
    },
    "98": {
        "tl": [
            84.42,
            228.55
        ],
        "tr": [
            90.28,
            228.67
        ],
        "br": [
            90.27,
            236.53
        ],
        "bl": [
            84.49,
            236.39
        ],
        "type": "grid"
    },
    "99": {
        "tl": [
            90.28,
            228.67
        ],
        "tr": [
            96.25,
            228.81
        ],
        "br": [
            96.18,
            236.61
        ],
        "bl": [
            90.27,
            236.53
        ],
        "type": "grid"
    },
    "100": {
        "tl": [
            96.25,
            228.81
        ],
        "tr": [
            102.03,
            228.82
        ],
        "br": [
            102.03,
            236.69
        ],
        "bl": [
            96.18,
            236.61
        ],
        "type": "grid"
    },
    "101": {
        "tl": [
            102.03,
            228.82
        ],
        "tr": [
            107.82,
            228.95
        ],
        "br": [
            107.88,
            236.76
        ],
        "bl": [
            102.03,
            236.69
        ],
        "type": "grid"
    },
    "102": {
        "tl": [
            107.82,
            228.95
        ],
        "tr": [
            113.67,
            228.97
        ],
        "br": [
            113.61,
            236.84
        ],
        "bl": [
            107.88,
            236.76
        ],
        "type": "grid"
    },
    "103": {
        "tl": [
            113.67,
            228.97
        ],
        "tr": [
            119.65,
            229.11
        ],
        "br": [
            119.6,
            236.98
        ],
        "bl": [
            113.61,
            236.84
        ],
        "type": "grid"
    },
    "104": {
        "tl": [
            143.2,
            229.41
        ],
        "tr": [
            148.96,
            229.54
        ],
        "br": [
            149.05,
            237.44
        ],
        "bl": [
            143.18,
            237.28
        ],
        "type": "grid"
    },
    "105": {
        "tl": [
            148.96,
            229.54
        ],
        "tr": [
            154.85,
            229.68
        ],
        "br": [
            154.88,
            237.45
        ],
        "bl": [
            149.05,
            237.44
        ],
        "type": "grid"
    },
    "106": {
        "tl": [
            154.85,
            229.68
        ],
        "tr": [
            160.68,
            229.69
        ],
        "br": [
            160.71,
            237.6
        ],
        "bl": [
            154.88,
            237.45
        ],
        "type": "grid"
    },
    "107": {
        "tl": [
            160.68,
            229.69
        ],
        "tr": [
            166.45,
            229.83
        ],
        "br": [
            166.49,
            237.73
        ],
        "bl": [
            160.71,
            237.6
        ],
        "type": "grid"
    },
    "108": {
        "tl": [
            166.45,
            229.83
        ],
        "tr": [
            172.29,
            229.97
        ],
        "br": [
            172.33,
            237.75
        ],
        "bl": [
            166.49,
            237.73
        ],
        "type": "grid"
    },
    "109": {
        "tl": [
            172.29,
            229.97
        ],
        "tr": [
            178.13,
            229.98
        ],
        "br": [
            178.17,
            237.89
        ],
        "bl": [
            172.33,
            237.75
        ],
        "type": "grid"
    },
    "110": {
        "tl": [
            178.13,
            229.98
        ],
        "tr": [
            184.17,
            230.06
        ],
        "br": [
            184.28,
            237.97
        ],
        "bl": [
            178.17,
            237.89
        ],
        "type": "grid"
    },
    "111": {
        "tl": [
            14.3,
            256.6
        ],
        "tr": [
            20.07,
            256.73
        ],
        "br": [
            20.01,
            264.59
        ],
        "bl": [
            14.21,
            264.44
        ],
        "type": "grid"
    },
    "112": {
        "tl": [
            20.07,
            256.73
        ],
        "tr": [
            25.8,
            256.75
        ],
        "br": [
            25.81,
            264.62
        ],
        "bl": [
            20.01,
            264.59
        ],
        "type": "grid"
    },
    "113": {
        "tl": [
            25.8,
            256.75
        ],
        "tr": [
            31.54,
            256.9
        ],
        "br": [
            31.5,
            264.71
        ],
        "bl": [
            25.81,
            264.62
        ],
        "type": "grid"
    },
    "114": {
        "tl": [
            31.54,
            256.9
        ],
        "tr": [
            37.41,
            256.93
        ],
        "br": [
            37.37,
            264.8
        ],
        "bl": [
            31.5,
            264.71
        ],
        "type": "grid"
    },
    "115": {
        "tl": [
            37.41,
            256.93
        ],
        "tr": [
            43.22,
            257.01
        ],
        "br": [
            43.25,
            264.89
        ],
        "bl": [
            37.37,
            264.8
        ],
        "type": "grid"
    },
    "116": {
        "tl": [
            43.22,
            257.01
        ],
        "tr": [
            49.14,
            257.12
        ],
        "br": [
            49.07,
            264.98
        ],
        "bl": [
            43.25,
            264.89
        ],
        "type": "grid"
    },
    "117": {
        "tl": [
            78.77,
            257.58
        ],
        "tr": [
            84.6,
            257.63
        ],
        "br": [
            84.65,
            265.53
        ],
        "bl": [
            78.8,
            265.38
        ],
        "type": "grid"
    },
    "118": {
        "tl": [
            84.6,
            257.63
        ],
        "tr": [
            90.45,
            257.78
        ],
        "br": [
            90.5,
            265.62
        ],
        "bl": [
            84.65,
            265.53
        ],
        "type": "grid"
    },
    "119": {
        "tl": [
            143.43,
            258.63
        ],
        "tr": [
            149.33,
            258.78
        ],
        "br": [
            149.36,
            266.65
        ],
        "bl": [
            143.46,
            266.5
        ],
        "type": "grid"
    },
    "120": {
        "tl": [
            149.33,
            258.78
        ],
        "tr": [
            155.15,
            258.89
        ],
        "br": [
            155.2,
            266.8
        ],
        "bl": [
            149.36,
            266.65
        ],
        "type": "grid"
    },
    "121": {
        "tl": [
            90.11,
            28.95
        ],
        "tr": [
            95.73,
            29.0
        ],
        "br": [
            95.66,
            36.56
        ],
        "bl": [
            90.03,
            36.5
        ],
        "type": "free"
    },
    "122": {
        "tl": [
            84.37,
            28.53
        ],
        "tr": [
            89.99,
            28.58
        ],
        "br": [
            89.92,
            36.13
        ],
        "bl": [
            84.29,
            36.07
        ],
        "type": "free"
    },
    "123": {
        "tl": [
            100.99,
            29.18
        ],
        "tr": [
            106.62,
            29.23
        ],
        "br": [
            106.56,
            36.79
        ],
        "bl": [
            100.92,
            36.73
        ],
        "type": "free"
    },
    "124": {
        "tl": [
            78.01,
            29.2
        ],
        "tr": [
            83.63,
            29.25
        ],
        "br": [
            83.55,
            36.8
        ],
        "bl": [
            77.94,
            36.74
        ],
        "type": "free"
    },
    "125": {
        "tl": [
            78.66,
            85.28
        ],
        "tr": [
            84.3,
            85.36
        ],
        "br": [
            84.22,
            92.97
        ],
        "bl": [
            78.58,
            92.89
        ],
        "type": "free"
    },
    "126": {
        "tl": [
            84.91,
            85.12
        ],
        "tr": [
            90.56,
            85.2
        ],
        "br": [
            90.49,
            92.82
        ],
        "bl": [
            84.84,
            92.74
        ],
        "type": "free"
    },
    "127": {
        "tl": [
            84.81,
            171.3
        ],
        "tr": [
            90.5,
            171.42
        ],
        "br": [
            90.43,
            179.14
        ],
        "bl": [
            84.74,
            179.03
        ],
        "type": "free"
    },
    "128": {
        "tl": [
            95.57,
            171.64
        ],
        "tr": [
            101.26,
            171.75
        ],
        "br": [
            101.2,
            179.48
        ],
        "bl": [
            95.5,
            179.37
        ],
        "type": "free"
    },
    "129": {
        "tl": [
            76.78,
            171.64
        ],
        "tr": [
            82.46,
            171.76
        ],
        "br": [
            82.39,
            179.48
        ],
        "bl": [
            76.7,
            179.36
        ],
        "type": "free"
    }
}