[
  {
    "id": "c1",
    "page": 10,
    "coins": {
      "tl": [
        14.26,
        28.68
      ],
      "tr": [
        20.06,
        28.72
      ],
      "bl": [
        14.25,
        36.34
      ],
      "br": [
        20.08,
        36.35
      ]
    }
  },
  {
    "id": "c2",
    "page": 10,
    "coins": {
      "tl": [
        20.06,
        28.72
      ],
      "tr": [
        25.88,
        28.76
      ],
      "bl": [
        20.08,
        36.35
      ],
      "br": [
        25.92,
        36.36
      ]
    }
  },
  {
    "id": "c3",
    "page": 10,
    "coins": {
      "tl": [
        25.88,
        28.76
      ],
      "tr": [
        31.37,
        28.74
      ],
      "bl": [
        25.92,
        36.36
      ],
      "br": [
        31.34,
        36.37
      ]
    }
  },
  {
    "id": "c4",
    "page": 10,
    "coins": {
      "tl": [
        31.37,
        28.74
      ],
      "tr": [
        37.08,
        28.68
      ],
      "bl": [
        31.34,
        36.37
      ],
      "br": [
        37.12,
        36.32
      ]
    }
  },
  {
    "id": "c5",
    "page": 10,
    "coins": {
      "tl": [
        37.08,
        28.68
      ],
      "tr": [
        42.93,
        28.69
      ],
      "bl": [
        37.12,
        36.32
      ],
      "br": [
        42.9,
        36.33
      ]
    }
  },
  {
    "id": "c6",
    "page": 10,
    "coins": {
      "tl": [
        42.93,
        28.69
      ],
      "tr": [
        48.77,
        28.7
      ],
      "bl": [
        42.9,
        36.33
      ],
      "br": [
        48.75,
        36.34
      ]
    }
  },
  {
    "id": "c7",
    "page": 10,
    "coins": {
      "tl": [
        48.77,
        28.7
      ],
      "tr": [
        54.6,
        28.66
      ],
      "bl": [
        48.75,
        36.34
      ],
      "br": [
        54.54,
        36.29
      ]
    }
  },
  {
    "id": "c8",
    "page": 10,
    "coins": {
      "tl": [
        141.51,
        28.85
      ],
      "tr": [
        147.25,
        28.78
      ],
      "bl": [
        141.55,
        36.44
      ],
      "br": [
        147.27,
        36.45
      ]
    }
  },
  {
    "id": "c9",
    "page": 10,
    "coins": {
      "tl": [
        147.25,
        28.78
      ],
      "tr": [
        152.91,
        28.85
      ],
      "bl": [
        147.27,
        36.45
      ],
      "br": [
        152.98,
        36.47
      ]
    }
  },
  {
    "id": "c10",
    "page": 10,
    "coins": {
      "tl": [
        152.91,
        28.85
      ],
      "tr": [
        158.62,
        28.8
      ],
      "bl": [
        152.98,
        36.47
      ],
      "br": [
        158.64,
        36.48
      ]
    }
  },
  {
    "id": "c11",
    "page": 10,
    "coins": {
      "tl": [
        158.62,
        28.8
      ],
      "tr": [
        164.28,
        28.75
      ],
      "bl": [
        158.64,
        36.48
      ],
      "br": [
        164.36,
        36.49
      ]
    }
  },
  {
    "id": "c12",
    "page": 10,
    "coins": {
      "tl": [
        164.28,
        28.75
      ],
      "tr": [
        170.0,
        28.82
      ],
      "bl": [
        164.36,
        36.49
      ],
      "br": [
        170.09,
        36.44
      ]
    }
  },
  {
    "id": "c13",
    "page": 10,
    "coins": {
      "tl": [
        14.31,
        57.01
      ],
      "tr": [
        20.09,
        57.08
      ],
      "bl": [
        14.28,
        64.66
      ],
      "br": [
        20.12,
        64.67
      ]
    }
  },
  {
    "id": "c14",
    "page": 10,
    "coins": {
      "tl": [
        20.09,
        57.08
      ],
      "tr": [
        25.94,
        57.03
      ],
      "bl": [
        20.12,
        64.67
      ],
      "br": [
        25.97,
        64.69
      ]
    }
  },
  {
    "id": "c15",
    "page": 10,
    "coins": {
      "tl": [
        25.94,
        57.03
      ],
      "tr": [
        31.36,
        56.99
      ],
      "bl": [
        25.97,
        64.69
      ],
      "br": [
        31.33,
        64.65
      ]
    }
  },
  {
    "id": "c16",
    "page": 10,
    "coins": {
      "tl": [
        31.36,
        56.99
      ],
      "tr": [
        37.08,
        57.07
      ],
      "bl": [
        31.33,
        64.65
      ],
      "br": [
        37.12,
        64.73
      ]
    }
  },
  {
    "id": "c17",
    "page": 10,
    "coins": {
      "tl": [
        37.08,
        57.07
      ],
      "tr": [
        42.94,
        57.02
      ],
      "bl": [
        37.12,
        64.73
      ],
      "br": [
        42.91,
        64.68
      ]
    }
  },
  {
    "id": "c18",
    "page": 10,
    "coins": {
      "tl": [
        42.94,
        57.02
      ],
      "tr": [
        48.77,
        56.99
      ],
      "bl": [
        42.91,
        64.68
      ],
      "br": [
        48.83,
        64.7
      ]
    }
  },
  {
    "id": "c19",
    "page": 10,
    "coins": {
      "tl": [
        78.01,
        57.12
      ],
      "tr": [
        83.73,
        57.19
      ],
      "bl": [
        78.03,
        64.78
      ],
      "br": [
        83.79,
        64.8
      ]
    }
  },
  {
    "id": "c20",
    "page": 10,
    "coins": {
      "tl": [
        83.73,
        57.19
      ],
      "tr": [
        89.49,
        57.14
      ],
      "bl": [
        83.79,
        64.8
      ],
      "br": [
        89.54,
        64.82
      ]
    }
  },
  {
    "id": "c21",
    "page": 10,
    "coins": {
      "tl": [
        89.49,
        57.14
      ],
      "tr": [
        95.35,
        57.17
      ],
      "bl": [
        89.54,
        64.82
      ],
      "br": [
        95.4,
        64.76
      ]
    }
  },
  {
    "id": "c22",
    "page": 10,
    "coins": {
      "tl": [
        141.63,
        57.22
      ],
      "tr": [
        147.29,
        57.3
      ],
      "bl": [
        141.61,
        64.96
      ],
      "br": [
        147.37,
        64.99
      ]
    }
  },
  {
    "id": "c23",
    "page": 10,
    "coins": {
      "tl": [
        147.29,
        57.3
      ],
      "tr": [
        153.05,
        57.27
      ],
      "bl": [
        147.37,
        64.99
      ],
      "br": [
        153.07,
        64.94
      ]
    }
  },
  {
    "id": "c24",
    "page": 10,
    "coins": {
      "tl": [
        14.3,
        85.27
      ],
      "tr": [
        20.13,
        85.28
      ],
      "bl": [
        14.32,
        92.98
      ],
      "br": [
        20.14,
        92.94
      ]
    }
  },
  {
    "id": "c25",
    "page": 10,
    "coins": {
      "tl": [
        141.69,
        85.65
      ],
      "tr": [
        147.45,
        85.65
      ],
      "bl": [
        141.73,
        93.34
      ],
      "br": [
        147.46,
        93.37
      ]
    }
  },
  {
    "id": "c26",
    "page": 10,
    "coins": {
      "tl": [
        147.45,
        85.65
      ],
      "tr": [
        153.12,
        85.74
      ],
      "bl": [
        147.46,
        93.37
      ],
      "br": [
        153.19,
        93.39
      ]
    }
  },
  {
    "id": "c27",
    "page": 10,
    "coins": {
      "tl": [
        153.12,
        85.74
      ],
      "tr": [
        158.89,
        85.71
      ],
      "bl": [
        153.19,
        93.39
      ],
      "br": [
        158.93,
        93.36
      ]
    }
  },
  {
    "id": "c28",
    "page": 10,
    "coins": {
      "tl": [
        14.25,
        113.72
      ],
      "tr": [
        20.11,
        113.75
      ],
      "bl": [
        14.27,
        121.41
      ],
      "br": [
        20.13,
        121.44
      ]
    }
  },
  {
    "id": "c29",
    "page": 10,
    "coins": {
      "tl": [
        20.11,
        113.75
      ],
      "tr": [
        25.97,
        113.77
      ],
      "bl": [
        20.13,
        121.44
      ],
      "br": [
        25.93,
        121.48
      ]
    }
  },
  {
    "id": "c30",
    "page": 10,
    "coins": {
      "tl": [
        25.97,
        113.77
      ],
      "tr": [
        31.34,
        113.74
      ],
      "bl": [
        25.93,
        121.48
      ],
      "br": [
        31.37,
        121.45
      ]
    }
  },
  {
    "id": "c31",
    "page": 10,
    "coins": {
      "tl": [
        31.34,
        113.74
      ],
      "tr": [
        37.08,
        113.84
      ],
      "bl": [
        31.37,
        121.45
      ],
      "br": [
        37.13,
        121.5
      ]
    }
  },
  {
    "id": "c32",
    "page": 10,
    "coins": {
      "tl": [
        37.08,
        113.84
      ],
      "tr": [
        42.95,
        113.8
      ],
      "bl": [
        37.13,
        121.5
      ],
      "br": [
        42.91,
        121.5
      ]
    }
  },
  {
    "id": "c33",
    "page": 10,
    "coins": {
      "tl": [
        78.1,
        113.98
      ],
      "tr": [
        83.81,
        113.94
      ],
      "bl": [
        78.17,
        121.68
      ],
      "br": [
        83.86,
        121.66
      ]
    }
  },
  {
    "id": "c34",
    "page": 10,
    "coins": {
      "tl": [
        83.81,
        113.94
      ],
      "tr": [
        89.64,
        114.04
      ],
      "bl": [
        83.86,
        121.66
      ],
      "br": [
        89.63,
        121.7
      ]
    }
  },
  {
    "id": "c35",
    "page": 10,
    "coins": {
      "tl": [
        89.64,
        114.04
      ],
      "tr": [
        95.47,
        114.0
      ],
      "bl": [
        89.63,
        121.7
      ],
      "br": [
        95.47,
        121.73
      ]
    }
  },
  {
    "id": "c36",
    "page": 10,
    "coins": {
      "tl": [
        95.47,
        114.0
      ],
      "tr": [
        101.2,
        114.05
      ],
      "bl": [
        95.47,
        121.73
      ],
      "br": [
        101.24,
        121.76
      ]
    }
  },
  {
    "id": "c37",
    "page": 10,
    "coins": {
      "tl": [
        101.2,
        114.05
      ],
      "tr": [
        106.96,
        114.06
      ],
      "bl": [
        101.24,
        121.76
      ],
      "br": [
        107.02,
        121.79
      ]
    }
  },
  {
    "id": "c38",
    "page": 10,
    "coins": {
      "tl": [
        106.96,
        114.06
      ],
      "tr": [
        112.8,
        114.15
      ],
      "bl": [
        107.02,
        121.79
      ],
      "br": [
        112.8,
        121.82
      ]
    }
  },
  {
    "id": "c39",
    "page": 10,
    "coins": {
      "tl": [
        112.8,
        114.15
      ],
      "tr": [
        118.56,
        114.13
      ],
      "bl": [
        112.8,
        121.82
      ],
      "br": [
        118.59,
        121.79
      ]
    }
  },
  {
    "id": "c40",
    "page": 10,
    "coins": {
      "tl": [
        141.71,
        114.25
      ],
      "tr": [
        147.48,
        114.27
      ],
      "bl": [
        141.78,
        121.96
      ],
      "br": [
        147.56,
        122.01
      ]
    }
  },
  {
    "id": "c41",
    "page": 10,
    "coins": {
      "tl": [
        147.48,
        114.27
      ],
      "tr": [
        153.28,
        114.3
      ],
      "bl": [
        147.56,
        122.01
      ],
      "br": [
        153.3,
        122.04
      ]
    }
  },
  {
    "id": "c42",
    "page": 10,
    "coins": {
      "tl": [
        153.28,
        114.3
      ],
      "tr": [
        159.01,
        114.36
      ],
      "bl": [
        153.3,
        122.04
      ],
      "br": [
        159.04,
        122.01
      ]
    }
  },
  {
    "id": "c43",
    "page": 10,
    "coins": {
      "tl": [
        159.01,
        114.36
      ],
      "tr": [
        164.71,
        114.36
      ],
      "bl": [
        159.04,
        122.01
      ],
      "br": [
        164.79,
        122.11
      ]
    }
  },
  {
    "id": "c44",
    "page": 10,
    "coins": {
      "tl": [
        164.71,
        114.36
      ],
      "tr": [
        170.52,
        114.39
      ],
      "bl": [
        164.79,
        122.11
      ],
      "br": [
        170.54,
        122.14
      ]
    }
  },
  {
    "id": "c45",
    "page": 10,
    "coins": {
      "tl": [
        170.52,
        114.39
      ],
      "tr": [
        176.2,
        114.42
      ],
      "bl": [
        170.54,
        122.14
      ],
      "br": [
        176.23,
        122.17
      ]
    }
  },
  {
    "id": "c46",
    "page": 10,
    "coins": {
      "tl": [
        176.2,
        114.42
      ],
      "tr": [
        182.14,
        114.45
      ],
      "bl": [
        176.23,
        122.17
      ],
      "br": [
        182.17,
        122.2
      ]
    }
  },
  {
    "id": "c47",
    "page": 10,
    "coins": {
      "tl": [
        182.14,
        114.45
      ],
      "tr": [
        187.88,
        114.43
      ],
      "bl": [
        182.17,
        122.2
      ],
      "br": [
        187.93,
        122.17
      ]
    }
  },
  {
    "id": "c48",
    "page": 10,
    "coins": {
      "tl": [
        14.22,
        142.32
      ],
      "tr": [
        20.08,
        142.29
      ],
      "bl": [
        14.24,
        149.98
      ],
      "br": [
        20.11,
        150.01
      ]
    }
  },
  {
    "id": "c49",
    "page": 10,
    "coins": {
      "tl": [
        20.08,
        142.29
      ],
      "tr": [
        25.97,
        142.36
      ],
      "bl": [
        20.11,
        150.01
      ],
      "br": [
        25.92,
        150.05
      ]
    }
  },
  {
    "id": "c50",
    "page": 10,
    "coins": {
      "tl": [
        25.97,
        142.36
      ],
      "tr": [
        31.33,
        142.37
      ],
      "bl": [
        25.92,
        150.05
      ],
      "br": [
        31.38,
        150.06
      ]
    }
  },
  {
    "id": "c51",
    "page": 10,
    "coins": {
      "tl": [
        31.33,
        142.37
      ],
      "tr": [
        37.21,
        142.34
      ],
      "bl": [
        31.38,
        150.06
      ],
      "br": [
        37.12,
        150.07
      ]
    }
  },
  {
    "id": "c52",
    "page": 10,
    "coins": {
      "tl": [
        37.21,
        142.34
      ],
      "tr": [
        42.96,
        142.44
      ],
      "bl": [
        37.12,
        150.07
      ],
      "br": [
        42.87,
        150.11
      ]
    }
  },
  {
    "id": "c53",
    "page": 10,
    "coins": {
      "tl": [
        42.96,
        142.44
      ],
      "tr": [
        48.84,
        142.41
      ],
      "bl": [
        42.87,
        150.11
      ],
      "br": [
        48.82,
        150.14
      ]
    }
  },
  {
    "id": "c54",
    "page": 10,
    "coins": {
      "tl": [
        48.84,
        142.41
      ],
      "tr": [
        54.64,
        142.4
      ],
      "bl": [
        48.82,
        150.14
      ],
      "br": [
        54.64,
        150.12
      ]
    }
  },
  {
    "id": "c55",
    "page": 10,
    "coins": {
      "tl": [
        78.19,
        142.54
      ],
      "tr": [
        83.87,
        142.63
      ],
      "bl": [
        78.21,
        150.33
      ],
      "br": [
        83.93,
        150.31
      ]
    }
  },
  {
    "id": "c56",
    "page": 10,
    "coins": {
      "tl": [
        83.87,
        142.63
      ],
      "tr": [
        89.71,
        142.61
      ],
      "bl": [
        83.93,
        150.31
      ],
      "br": [
        89.71,
        150.35
      ]
    }
  },
  {
    "id": "c57",
    "page": 10,
    "coins": {
      "tl": [
        89.71,
        142.61
      ],
      "tr": [
        95.49,
        142.7
      ],
      "bl": [
        89.71,
        150.35
      ],
      "br": [
        95.55,
        150.39
      ]
    }
  },
  {
    "id": "c58",
    "page": 10,
    "coins": {
      "tl": [
        95.49,
        142.7
      ],
      "tr": [
        101.28,
        142.68
      ],
      "bl": [
        95.55,
        150.39
      ],
      "br": [
        101.33,
        150.43
      ]
    }
  },
  {
    "id": "c59",
    "page": 10,
    "coins": {
      "tl": [
        101.28,
        142.68
      ],
      "tr": [
        107.06,
        142.68
      ],
      "bl": [
        101.33,
        150.43
      ],
      "br": [
        107.12,
        150.47
      ]
    }
  },
  {
    "id": "c60",
    "page": 10,
    "coins": {
      "tl": [
        141.84,
        143.0
      ],
      "tr": [
        147.64,
        142.97
      ],
      "bl": [
        141.91,
        150.7
      ],
      "br": [
        147.66,
        150.74
      ]
    }
  },
  {
    "id": "c61",
    "page": 10,
    "coins": {
      "tl": [
        147.64,
        142.97
      ],
      "tr": [
        153.33,
        143.07
      ],
      "bl": [
        147.66,
        150.74
      ],
      "br": [
        153.41,
        150.78
      ]
    }
  },
  {
    "id": "c62",
    "page": 10,
    "coins": {
      "tl": [
        153.33,
        143.07
      ],
      "tr": [
        159.14,
        143.05
      ],
      "bl": [
        153.41,
        150.78
      ],
      "br": [
        159.16,
        150.81
      ]
    }
  },
  {
    "id": "c63",
    "page": 10,
    "coins": {
      "tl": [
        159.14,
        143.05
      ],
      "tr": [
        164.89,
        143.08
      ],
      "bl": [
        159.16,
        150.81
      ],
      "br": [
        164.98,
        150.85
      ]
    }
  },
  {
    "id": "c64",
    "page": 10,
    "coins": {
      "tl": [
        164.89,
        143.08
      ],
      "tr": [
        170.65,
        143.12
      ],
      "bl": [
        164.98,
        150.85
      ],
      "br": [
        170.67,
        150.89
      ]
    }
  },
  {
    "id": "c65",
    "page": 10,
    "coins": {
      "tl": [
        170.65,
        143.12
      ],
      "tr": [
        176.34,
        143.16
      ],
      "bl": [
        170.67,
        150.89
      ],
      "br": [
        176.43,
        150.93
      ]
    }
  },
  {
    "id": "c66",
    "page": 10,
    "coins": {
      "tl": [
        176.34,
        143.16
      ],
      "tr": [
        182.29,
        143.2
      ],
      "bl": [
        176.43,
        150.93
      ],
      "br": [
        182.38,
        150.91
      ]
    }
  },
  {
    "id": "c67",
    "page": 10,
    "coins": {
      "tl": [
        14.25,
        170.88
      ],
      "tr": [
        20.06,
        170.86
      ],
      "bl": [
        14.22,
        178.6
      ],
      "br": [
        20.08,
        178.6
      ]
    }
  },
  {
    "id": "c68",
    "page": 10,
    "coins": {
      "tl": [
        141.99,
        171.71
      ],
      "tr": [
        147.74,
        171.7
      ],
      "bl": [
        142.0,
        179.5
      ],
      "br": [
        147.76,
        179.48
      ]
    }
  },
  {
    "id": "c69",
    "page": 10,
    "coins": {
      "tl": [
        147.74,
        171.7
      ],
      "tr": [
        153.5,
        171.8
      ],
      "bl": [
        147.76,
        179.48
      ],
      "br": [
        153.59,
        179.55
      ]
    }
  },
  {
    "id": "c70",
    "page": 10,
    "coins": {
      "tl": [
        153.5,
        171.8
      ],
      "tr": [
        159.32,
        171.78
      ],
      "bl": [
        153.59,
        179.55
      ],
      "br": [
        159.34,
        179.57
      ]
    }
  },
  {
    "id": "c71",
    "page": 10,
    "coins": {
      "tl": [
        159.32,
        171.78
      ],
      "tr": [
        165.08,
        171.83
      ],
      "bl": [
        159.34,
        179.57
      ],
      "br": [
        165.1,
        179.62
      ]
    }
  },
  {
    "id": "c72",
    "page": 10,
    "coins": {
      "tl": [
        14.22,
        199.36
      ],
      "tr": [
        20.03,
        199.38
      ],
      "bl": [
        14.19,
        207.14
      ],
      "br": [
        20.06,
        207.15
      ]
    }
  },
  {
    "id": "c73",
    "page": 10,
    "coins": {
      "tl": [
        20.03,
        199.38
      ],
      "tr": [
        25.98,
        199.5
      ],
      "bl": [
        20.06,
        207.15
      ],
      "br": [
        26.01,
        207.2
      ]
    }
  },
  {
    "id": "c74",
    "page": 10,
    "coins": {
      "tl": [
        25.98,
        199.5
      ],
      "tr": [
        31.38,
        199.49
      ],
      "bl": [
        26.01,
        207.2
      ],
      "br": [
        31.41,
        207.25
      ]
    }
  },
  {
    "id": "c75",
    "page": 10,
    "coins": {
      "tl": [
        78.29,
        199.84
      ],
      "tr": [
        84.01,
        199.88
      ],
      "bl": [
        78.33,
        207.61
      ],
      "br": [
        84.0,
        207.67
      ]
    }
  },
  {
    "id": "c76",
    "page": 10,
    "coins": {
      "tl": [
        84.01,
        199.88
      ],
      "tr": [
        89.86,
        199.93
      ],
      "bl": [
        84.0,
        207.67
      ],
      "br": [
        89.8,
        207.66
      ]
    }
  },
  {
    "id": "c77",
    "page": 10,
    "coins": {
      "tl": [
        89.86,
        199.93
      ],
      "tr": [
        95.66,
        199.98
      ],
      "bl": [
        89.8,
        207.66
      ],
      "br": [
        95.72,
        207.77
      ]
    }
  },
  {
    "id": "c78",
    "page": 10,
    "coins": {
      "tl": [
        95.66,
        199.98
      ],
      "tr": [
        101.46,
        200.03
      ],
      "bl": [
        95.72,
        207.77
      ],
      "br": [
        101.52,
        207.76
      ]
    }
  },
  {
    "id": "c79",
    "page": 10,
    "coins": {
      "tl": [
        101.46,
        200.03
      ],
      "tr": [
        107.26,
        200.08
      ],
      "bl": [
        101.52,
        207.76
      ],
      "br": [
        107.33,
        207.88
      ]
    }
  },
  {
    "id": "c80",
    "page": 10,
    "coins": {
      "tl": [
        107.26,
        200.08
      ],
      "tr": [
        113.07,
        200.07
      ],
      "bl": [
        107.33,
        207.88
      ],
      "br": [
        113.13,
        207.87
      ]
    }
  },
  {
    "id": "c81",
    "page": 10,
    "coins": {
      "tl": [
        113.07,
        200.07
      ],
      "tr": [
        118.88,
        200.18
      ],
      "bl": [
        113.13,
        207.87
      ],
      "br": [
        118.94,
        207.98
      ]
    }
  },
  {
    "id": "c82",
    "page": 10,
    "coins": {
      "tl": [
        118.88,
        200.18
      ],
      "tr": [
        124.57,
        200.17
      ],
      "bl": [
        118.94,
        207.98
      ],
      "br": [
        124.63,
        207.97
      ]
    }
  },
  {
    "id": "c83",
    "page": 10,
    "coins": {
      "tl": [
        142.08,
        200.39
      ],
      "tr": [
        147.84,
        200.38
      ],
      "bl": [
        142.13,
        208.18
      ],
      "br": [
        147.92,
        208.19
      ]
    }
  },
  {
    "id": "c84",
    "page": 10,
    "coins": {
      "tl": [
        147.84,
        200.38
      ],
      "tr": [
        153.66,
        200.49
      ],
      "bl": [
        147.92,
        208.19
      ],
      "br": [
        153.74,
        208.24
      ]
    }
  },
  {
    "id": "c85",
    "page": 10,
    "coins": {
      "tl": [
        153.66,
        200.49
      ],
      "tr": [
        159.49,
        200.48
      ],
      "bl": [
        153.74,
        208.24
      ],
      "br": [
        159.51,
        208.29
      ]
    }
  },
  {
    "id": "c86",
    "page": 10,
    "coins": {
      "tl": [
        159.49,
        200.48
      ],
      "tr": [
        165.26,
        200.59
      ],
      "bl": [
        159.51,
        208.29
      ],
      "br": [
        165.35,
        208.35
      ]
    }
  },
  {
    "id": "c87",
    "page": 10,
    "coins": {
      "tl": [
        165.26,
        200.59
      ],
      "tr": [
        171.03,
        200.58
      ],
      "bl": [
        165.35,
        208.35
      ],
      "br": [
        171.12,
        208.4
      ]
    }
  },
  {
    "id": "c88",
    "page": 10,
    "coins": {
      "tl": [
        171.03,
        200.58
      ],
      "tr": [
        176.75,
        200.7
      ],
      "bl": [
        171.12,
        208.4
      ],
      "br": [
        176.83,
        208.45
      ]
    }
  },
  {
    "id": "c89",
    "page": 10,
    "coins": {
      "tl": [
        176.75,
        200.7
      ],
      "tr": [
        182.71,
        200.69
      ],
      "bl": [
        176.83,
        208.45
      ],
      "br": [
        182.74,
        208.5
      ]
    }
  },
  {
    "id": "c90",
    "page": 10,
    "coins": {
      "tl": [
        182.71,
        200.69
      ],
      "tr": [
        188.53,
        200.69
      ],
      "bl": [
        182.74,
        208.5
      ],
      "br": [
        188.63,
        208.48
      ]
    }
  },
  {
    "id": "c91",
    "page": 10,
    "coins": {
      "tl": [
        14.26,
        228.07
      ],
      "tr": [
        20.13,
        228.12
      ],
      "bl": [
        14.28,
        235.89
      ],
      "br": [
        20.1,
        235.9
      ]
    }
  },
  {
    "id": "c92",
    "page": 10,
    "coins": {
      "tl": [
        20.13,
        228.12
      ],
      "tr": [
        25.96,
        228.17
      ],
      "bl": [
        20.1,
        235.9
      ],
      "br": [
        25.99,
        235.9
      ]
    }
  },
  {
    "id": "c93",
    "page": 10,
    "coins": {
      "tl": [
        25.96,
        228.17
      ],
      "tr": [
        31.43,
        228.23
      ],
      "bl": [
        25.99,
        235.9
      ],
      "br": [
        31.46,
        236.02
      ]
    }
  },
  {
    "id": "c94",
    "page": 10,
    "coins": {
      "tl": [
        31.43,
        228.23
      ],
      "tr": [
        37.21,
        228.29
      ],
      "bl": [
        31.46,
        236.02
      ],
      "br": [
        37.24,
        236.02
      ]
    }
  },
  {
    "id": "c95",
    "page": 10,
    "coins": {
      "tl": [
        37.21,
        228.29
      ],
      "tr": [
        43.0,
        228.32
      ],
      "bl": [
        37.24,
        236.02
      ],
      "br": [
        43.02,
        236.02
      ]
    }
  },
  {
    "id": "c96",
    "page": 10,
    "coins": {
      "tl": [
        43.0,
        228.32
      ],
      "tr": [
        48.89,
        228.34
      ],
      "bl": [
        43.02,
        236.02
      ],
      "br": [
        48.9,
        236.06
      ]
    }
  },
  {
    "id": "c97",
    "page": 10,
    "coins": {
      "tl": [
        78.36,
        228.58
      ],
      "tr": [
        84.08,
        228.56
      ],
      "bl": [
        78.34,
        236.35
      ],
      "br": [
        84.13,
        236.37
      ]
    }
  },
  {
    "id": "c98",
    "page": 10,
    "coins": {
      "tl": [
        84.08,
        228.56
      ],
      "tr": [
        89.88,
        228.69
      ],
      "bl": [
        84.13,
        236.37
      ],
      "br": [
        89.81,
        236.43
      ]
    }
  },
  {
    "id": "c99",
    "page": 10,
    "coins": {
      "tl": [
        89.88,
        228.69
      ],
      "tr": [
        95.79,
        228.7
      ],
      "bl": [
        89.81,
        236.43
      ],
      "br": [
        95.74,
        236.49
      ]
    }
  },
  {
    "id": "c100",
    "page": 10,
    "coins": {
      "tl": [
        95.79,
        228.7
      ],
      "tr": [
        101.55,
        228.8
      ],
      "bl": [
        95.74,
        236.49
      ],
      "br": [
        101.55,
        236.55
      ]
    }
  },
  {
    "id": "c101",
    "page": 10,
    "coins": {
      "tl": [
        101.55,
        228.8
      ],
      "tr": [
        107.43,
        228.8
      ],
      "bl": [
        101.55,
        236.55
      ],
      "br": [
        107.36,
        236.61
      ]
    }
  },
  {
    "id": "c102",
    "page": 10,
    "coins": {
      "tl": [
        107.43,
        228.8
      ],
      "tr": [
        113.18,
        228.92
      ],
      "bl": [
        107.36,
        236.61
      ],
      "br": [
        113.18,
        236.67
      ]
    }
  },
  {
    "id": "c103",
    "page": 10,
    "coins": {
      "tl": [
        113.18,
        228.92
      ],
      "tr": [
        119.0,
        228.91
      ],
      "bl": [
        113.18,
        236.67
      ],
      "br": [
        119.06,
        236.67
      ]
    }
  },
  {
    "id": "c104",
    "page": 10,
    "coins": {
      "tl": [
        142.2,
        229.23
      ],
      "tr": [
        148.0,
        229.27
      ],
      "bl": [
        142.24,
        236.97
      ],
      "br": [
        148.08,
        237.1
      ]
    }
  },
  {
    "id": "c105",
    "page": 10,
    "coins": {
      "tl": [
        148.0,
        229.27
      ],
      "tr": [
        153.83,
        229.33
      ],
      "bl": [
        148.08,
        237.1
      ],
      "br": [
        153.91,
        237.1
      ]
    }
  },
  {
    "id": "c106",
    "page": 10,
    "coins": {
      "tl": [
        153.83,
        229.33
      ],
      "tr": [
        159.67,
        229.38
      ],
      "bl": [
        153.91,
        237.1
      ],
      "br": [
        159.75,
        237.22
      ]
    }
  },
  {
    "id": "c107",
    "page": 10,
    "coins": {
      "tl": [
        159.67,
        229.38
      ],
      "tr": [
        165.45,
        229.38
      ],
      "bl": [
        159.75,
        237.22
      ],
      "br": [
        165.53,
        237.22
      ]
    }
  },
  {
    "id": "c108",
    "page": 10,
    "coins": {
      "tl": [
        165.45,
        229.38
      ],
      "tr": [
        171.23,
        229.5
      ],
      "bl": [
        165.53,
        237.22
      ],
      "br": [
        171.33,
        237.3
      ]
    }
  },
  {
    "id": "c109",
    "page": 10,
    "coins": {
      "tl": [
        171.23,
        229.5
      ],
      "tr": [
        176.95,
        229.56
      ],
      "bl": [
        171.33,
        237.3
      ],
      "br": [
        177.04,
        237.34
      ]
    }
  },
  {
    "id": "c110",
    "page": 10,
    "coins": {
      "tl": [
        176.95,
        229.56
      ],
      "tr": [
        182.92,
        229.62
      ],
      "bl": [
        177.04,
        237.34
      ],
      "br": [
        183.01,
        237.4
      ]
    }
  },
  {
    "id": "c111",
    "page": 10,
    "coins": {
      "tl": [
        14.28,
        256.89
      ],
      "tr": [
        20.11,
        256.93
      ],
      "bl": [
        14.29,
        264.67
      ],
      "br": [
        20.13,
        264.74
      ]
    }
  },
  {
    "id": "c112",
    "page": 10,
    "coins": {
      "tl": [
        20.11,
        256.93
      ],
      "tr": [
        25.95,
        256.93
      ],
      "bl": [
        20.13,
        264.74
      ],
      "br": [
        25.98,
        264.74
      ]
    }
  },
  {
    "id": "c113",
    "page": 10,
    "coins": {
      "tl": [
        25.95,
        256.93
      ],
      "tr": [
        31.48,
        257.06
      ],
      "bl": [
        25.98,
        264.74
      ],
      "br": [
        31.51,
        264.87
      ]
    }
  },
  {
    "id": "c114",
    "page": 10,
    "coins": {
      "tl": [
        31.48,
        257.06
      ],
      "tr": [
        37.27,
        257.06
      ],
      "bl": [
        31.51,
        264.87
      ],
      "br": [
        37.24,
        264.88
      ]
    }
  },
  {
    "id": "c115",
    "page": 10,
    "coins": {
      "tl": [
        37.27,
        257.06
      ],
      "tr": [
        42.99,
        257.06
      ],
      "bl": [
        37.24,
        264.88
      ],
      "br": [
        43.03,
        264.88
      ]
    }
  },
  {
    "id": "c116",
    "page": 10,
    "coins": {
      "tl": [
        42.99,
        257.06
      ],
      "tr": [
        48.91,
        257.19
      ],
      "bl": [
        43.03,
        264.88
      ],
      "br": [
        48.95,
        264.95
      ]
    }
  },
  {
    "id": "c117",
    "page": 10,
    "coins": {
      "tl": [
        78.4,
        257.46
      ],
      "tr": [
        84.14,
        257.46
      ],
      "bl": [
        78.45,
        265.22
      ],
      "br": [
        84.13,
        265.29
      ]
    }
  },
  {
    "id": "c118",
    "page": 10,
    "coins": {
      "tl": [
        84.14,
        257.46
      ],
      "tr": [
        90.02,
        257.59
      ],
      "bl": [
        84.13,
        265.29
      ],
      "br": [
        90.01,
        265.36
      ]
    }
  },
  {
    "id": "c119",
    "page": 10,
    "coins": {
      "tl": [
        142.38,
        258.11
      ],
      "tr": [
        148.22,
        258.24
      ],
      "bl": [
        142.42,
        266.01
      ],
      "br": [
        148.24,
        266.03
      ]
    }
  },
  {
    "id": "c120",
    "page": 10,
    "coins": {
      "tl": [
        148.22,
        258.24
      ],
      "tr": [
        154.0,
        258.24
      ],
      "bl": [
        148.24,
        266.03
      ],
      "br": [
        154.08,
        266.04
      ]
    }
  },
  {
    "id": "c121",
    "page": 10,
    "coins": {
      "tl": [
        77.8,
        28.13
      ],
      "tr": [
        83.42,
        28.08
      ],
      "bl": [
        77.85,
        35.72
      ],
      "br": [
        83.47,
        35.67
      ]
    }
  },
  {
    "id": "c122",
    "page": 10,
    "coins": {
      "tl": [
        83.3,
        28.69
      ],
      "tr": [
        88.92,
        28.64
      ],
      "bl": [
        83.35,
        36.28
      ],
      "br": [
        88.97,
        36.23
      ]
    }
  },
  {
    "id": "c123",
    "page": 10,
    "coins": {
      "tl": [
        89.29,
        29.25
      ],
      "tr": [
        94.92,
        29.2
      ],
      "bl": [
        89.35,
        36.84
      ],
      "br": [
        94.97,
        36.79
      ]
    }
  },
  {
    "id": "c124",
    "page": 10,
    "coins": {
      "tl": [
        95.41,
        29.44
      ],
      "tr": [
        101.04,
        29.39
      ],
      "bl": [
        95.46,
        37.03
      ],
      "br": [
        101.09,
        36.98
      ]
    }
  },
  {
    "id": "c125",
    "page": 10,
    "coins": {
      "tl": [
        100.91,
        29.26
      ],
      "tr": [
        106.54,
        29.21
      ],
      "bl": [
        100.97,
        36.86
      ],
      "br": [
        106.6,
        36.81
      ]
    }
  },
  {
    "id": "c126",
    "page": 10,
    "coins": {
      "tl": [
        83.32,
        86.27
      ],
      "tr": [
        88.95,
        86.23
      ],
      "bl": [
        83.37,
        93.9
      ],
      "br": [
        89.01,
        93.87
      ]
    }
  },
  {
    "id": "c127",
    "page": 10,
    "coins": {
      "tl": [
        77.8,
        86.18
      ],
      "tr": [
        83.44,
        86.14
      ],
      "bl": [
        77.85,
        93.82
      ],
      "br": [
        83.49,
        93.78
      ]
    }
  },
  {
    "id": "c128",
    "page": 10,
    "coins": {
      "tl": [
        89.54,
        171.44
      ],
      "tr": [
        95.21,
        171.43
      ],
      "bl": [
        89.6,
        179.15
      ],
      "br": [
        95.26,
        179.13
      ]
    }
  },
  {
    "id": "c129",
    "page": 10,
    "coins": {
      "tl": [
        78.23,
        171.98
      ],
      "tr": [
        83.89,
        171.96
      ],
      "bl": [
        78.27,
        179.68
      ],
      "br": [
        83.94,
        179.66
      ]
    }
  },
  {
    "id": "c130",
    "page": 10,
    "coins": {
      "tl": [
        83.64,
        171.71
      ],
      "tr": [
        89.3,
        171.69
      ],
      "bl": [
        83.69,
        179.41
      ],
      "br": [
        89.35,
        179.4
      ]
    }
  },
  {
    "id": "c131",
    "page": 10,
    "coins": {
      "tl": [
        94.35,
        172.3
      ],
      "tr": [
        100.02,
        172.28
      ],
      "bl": [
        94.41,
        180.01
      ],
      "br": [
        100.08,
        179.99
      ]
    }
  }
]